agent_memory_server/__init__.py
agent_memory_server/api.py
agent_memory_server/auth.py
agent_memory_server/cli.py
agent_memory_server/config.py
agent_memory_server/dependencies.py
agent_memory_server/docket_tasks.py
agent_memory_server/extraction.py
agent_memory_server/filters.py
agent_memory_server/healthcheck.py
agent_memory_server/logging.py
agent_memory_server/long_term_memory.py
agent_memory_server/main.py
agent_memory_server/mcp.py
agent_memory_server/memory_strategies.py
agent_memory_server/migrations.py
agent_memory_server/models.py
agent_memory_server/prompt_security.py
agent_memory_server/summarization.py
agent_memory_server/summary_views.py
agent_memory_server/tasks.py
agent_memory_server/vectorstore_adapter.py
agent_memory_server/vectorstore_factory.py
agent_memory_server/working_memory.py
agent_memory_server/_aws/__init__.py
agent_memory_server/_aws/clients.py
agent_memory_server/_aws/utils.py
agent_memory_server/llm/__init__.py
agent_memory_server/llm/client.py
agent_memory_server/llm/embeddings.py
agent_memory_server/llm/exceptions.py
agent_memory_server/llm/types.py
agent_memory_server/utils/__init__.py
agent_memory_server/utils/api_keys.py
agent_memory_server/utils/keys.py
agent_memory_server/utils/recency.py
agent_memory_server/utils/redis.py
agent_memory_server/utils/redis_query.py
agent_memory_server-0.13.0.dist-info/METADATA
agent_memory_server-0.13.0.dist-info/WHEEL
agent_memory_server-0.13.0.dist-info/entry_points.txt
agent_memory_server-0.13.0.dist-info/licenses/LICENSE
agent_memory_server-0.13.0.dist-info/RECORD
