Metadata-Version: 2.4
Name: agent-memory-server
Version: 0.13.0
Summary: A Memory Server for LLM Agents and Applications
Project-URL: Homepage, https://github.com/redis-developer/agent-memory-server
Project-URL: Repository, https://github.com/redis-developer/agent-memory-server
Project-URL: Documentation, https://github.com/redis-developer/agent-memory-server/tree/main/docs
Project-URL: Issues, https://github.com/redis-developer/agent-memory-server/issues
Author-email: Andrew Brookins <andrew.brookins@redis.com>
License: Apache-2.0
License-File: LICENSE
Requires-Python: <3.13,>=3.12
Requires-Dist: agent-memory-client
Requires-Dist: anthropic>=0.15.0
Requires-Dist: bcrypt>=4.0.0
Requires-Dist: cachetools<7.0.0,>=6.2.2
Requires-Dist: click>=8.1.0
Requires-Dist: cryptography>=3.4.8
Requires-Dist: fastapi>=0.115.11
Requires-Dist: httpx>=0.25.0
Requires-Dist: langchain-community>=0.3.27
Requires-Dist: langchain-core>=0.3.0
Requires-Dist: langchain-openai>=0.3.18
Requires-Dist: langchain-redis>=0.2.1
Requires-Dist: litellm>=1.80.11
Requires-Dist: mcp>=1.6.0
Requires-Dist: numpy>=2.1.0
Requires-Dist: openai>=1.3.7
Requires-Dist: pydantic-settings>=2.8.1
Requires-Dist: pydantic>=2.5.2
Requires-Dist: pydocket>=0.6.3
Requires-Dist: python-dotenv>=1.0.0
Requires-Dist: python-jose[cryptography]>=3.3.0
Requires-Dist: python-ulid>=3.0.0
Requires-Dist: pyyaml>=6.0
Requires-Dist: redisvl>=0.6.0
Requires-Dist: sniffio>=1.3.1
Requires-Dist: structlog>=25.2.0
Requires-Dist: tiktoken>=0.5.1
Requires-Dist: transformers>=4.51.1
Requires-Dist: uvicorn>=0.24.0
Provides-Extra: aws
Requires-Dist: boto3<2.0.0,>=1.42.1; extra == 'aws'
Requires-Dist: botocore<2.0.0,>=1.42.1; extra == 'aws'
Requires-Dist: langchain-aws<2.0.0,>=1.1.0; extra == 'aws'
Provides-Extra: dev
Requires-Dist: agent-memory-client; extra == 'dev'
